Workbook
Name aporte: APP!$D$16
Name patrimonio_acumulado: APP!$D$19
Name periodo: APP!$D$17
Name rendimento_carteira: APP!$D$12
Name salario: APP!$D$11
Name sugestao_invest: APP!$D$13
Name taxa_mensal: APP!$D$18

Sheet APP
B10: CONFIGURAÇÕES
B11: Salário | D11: 3000
B12: Rendimento da Carteira | D12: 0.01
B13: Sugestão de investimento | D13: =salario*30% -> 900
B15: INVESTIMENTO MENSAL
B16: Quanto investir ao mês | D16: 1500
B17: Por quantos anos | D17: 5
B18: Taxa de rendimento mensal | D18: 0.01079
B19: Patrimônio acumulado | D19: =FV(taxa_mensal,periodo*12,aporte*-1) -> 125665.37
B20: Dividendos mensais | D20: =patrimonio_acumulado*rendimento_carteira -> 1256.6537
B22: CENÁRIOS | D22: Dividendos
A23: 2 | B23: 2 Anos | C23: =FV($D$18,A23*12,$D$16*-1) -> 40841.441 | D23: =C23*rendimento_carteira -> 408.41441
A24: 5 | B24: 5 Anos | C24: =FV($D$18,A24*12,$D$16*-1) -> 125665.37 | D24: =C24*rendimento_carteira -> 1256.6537
A25: 10 | B25: 10 Anos | C25: =FV($D$18,A25*12,$D$16*-1) -> 364926.32 | D25: =C25*rendimento_carteira -> 3649.2632
A26: 20 | B26: 20 Anos | C26: =FV($D$18,A26*12,$D$16*-1) -> 1687797.6 | D26: =C26*rendimento_carteira -> 16877.976
A27: 30 | B27: 30 Anos | C27: =FV($D$18,A27*12,$D$16*-1) -> 6483254.5 | D27: =C27*rendimento_carteira -> 64832.545
B29: PERFIL | D29: Conservador
B30: Valor Mensal | D30: 300
B32: TIPOS DE FIIs | C32: Percentual Sugerido | D32: Valores
B33: PAPEL | C33: =VLOOKUP($D$29&"-"&B33,Tab_apoio!$B$3:$E$20,4,FALSE) -> 0.3 | D33: =C33*$D$30 -> 90
B34: TIJOLO | C34: =VLOOKUP($D$29&"-"&B34,Tab_apoio!$B$3:$E$20,4,FALSE) -> 0.5 | D34: =C34*$D$30 -> 150
B35: HÍBRIDOS | C35: =VLOOKUP($D$29&"-"&B35,Tab_apoio!$B$3:$E$20,4,FALSE) -> 0.1 | D35: =C35*$D$30 -> 30
B36: FOFs | C36: =VLOOKUP($D$29&"-"&B36,Tab_apoio!$B$3:$E$20,4,FALSE) -> 0.1 | D36: =C36*$D$30 -> 30
B37: DESENVOLVIMENTO | C37: =VLOOKUP($D$29&"-"&B37,Tab_apoio!$B$3:$E$20,4,FALSE) -> 0 | D37: =C37*$D$30 -> 0
B38: HOTELARIAS | C38: =VLOOKUP($D$29&"-"&B38,Tab_apoio!$B$3:$E$20,4,FALSE) -> 0 | D38: =C38*$D$30 -> 0
B39: TOTAL | C39: =SUM(C33:C38) -> 1 | D39: =SUM(D33:D38) -> 300

Sheet Tab_apoio
B2: CHAVE | C2: Perfil | D2: Tipo de FII | E2: %
B3: =C3&"-"&D3 -> Conservador-PAPEL | C3: Conservador | D3: PAPEL | E3: 0.3
B4: =C4&"-"&D4 -> Conservador-TIJOLO | C4: Conservador | D4: TIJOLO | E4: 0.5
B5: =C5&"-"&D5 -> Conservador-HÍBRIDOS | C5: Conservador | D5: HÍBRIDOS | E5: 0.1
B6: =C6&"-"&D6 -> Conservador-FOFs | C6: Conservador | D6: FOFs | E6: 0.1
B7: =C7&"-"&D7 -> Conservador-DESENVOLVIMENTO | C7: Conservador | D7: DESENVOLVIMENTO | E7: 0
B8: =C8&"-"&D8 -> Conservador-HOTELARIAS | C8: Conservador | D8: HOTELARIAS | E8: 0
B9: =C9&"-"&D9 -> Moderado-PAPEL | C9: Moderado | D9: PAPEL | E9: 0.32
B10: =C10&"-"&D10 -> Moderado-TIJOLO | C10: Moderado | D10: TIJOLO | E10: 0.35
B11: =C11&"-"&D11 -> Moderado-HÍBRIDOS | C11: Moderado | D11: HÍBRIDOS | E11: 0.08
B12: =C12&"-"&D12 -> Moderado-FOFs | C12: Moderado | D12: FOFs | E12: 0.05
B13: =C13&"-"&D13 -> Moderado-DESENVOLVIMENTO | C13: Moderado | D13: DESENVOLVIMENTO | E13: 0.1
B14: =C14&"-"&D14 -> Moderado-HOTELARIAS | C14: Moderado | D14: HOTELARIAS | E14: 0.1
... B20: =C20&"-"&D20 -> Agressivo-HOTELARIAS | C20: Agressivo | D20: HOTELARIAS | E20: 0.1
